{
 "cells": [
  {
   "cell_type": "code",
   "execution_count": 9,
   "metadata": {},
   "outputs": [],
   "source": [
    "class Interpreter:\n",
    "    def __init__(self):\n",
    "        self.stack = [] # [7, 4, 8]\n",
    "        self.environment = {} # {\"x\": 7, \"y\": 4, \"z\": 8}\n",
    "\n",
    "    def LOAD_VALUE(self, number):\n",
    "        self.stack.append(number)\n",
    "    \n",
    "    def STORE_NAME(self, name):\n",
    "        value = self.stack.pop()\n",
    "        self.environment[name] = value\n",
    "\n",
    "    def LOAD_NAME(self, name):\n",
    "        value = self.environment[name]\n",
    "        self.stack.append(value)\n",
    "    \n",
    "    def PRINT_ANSWER(self):\n",
    "        answer = self.stack.pop()\n",
    "        print(answer)\n",
    "    \n",
    "    def ADD_TWO_VALUES(self):\n",
    "        first_num = self.stack.pop()\n",
    "        second_num = self.stack.pop()\n",
    "        total = first_num + second_num\n",
    "        self.stack.append(total)\n",
    "    \n",
    "    def parse_argument(self, instruction, argument, what_to_execute):\n",
    "        numbers = [\"LOAD_VALUE\"]\n",
    "        names = [\"LOAD_NAME\", \"STORE_NAME\"]\n",
    "        if instruction in numbers:\n",
    "            argument = what_to_execute[\"numbers\"][argument]\n",
    "        elif instruction in names:\n",
    "            argument = what_to_execute[\"names\"][argument]\n",
    "        return argument\n",
    "    \n",
    "    def run_code(self, what_to_execute):\n",
    "        instructions = what_to_execute[\"instructions\"]\n",
    "        for each_step in instructions:\n",
    "            instruction, argument = each_step\n",
    "            argument = self.parse_argument(instruction, argument, what_to_execute)\n",
    "\n",
    "            if instruction == \"LOAD_VALUE\":\n",
    "                self.LOAD_VALUE(argument)\n",
    "            elif instruction == \"ADD_TWO_VALUES\":\n",
    "                self.ADD_TWO_VALUES()\n",
    "            elif instruction == \"PRINT_ANSWER\":\n",
    "                self.PRINT_ANSWER()\n",
    "            elif instruction == \"STORE_NAME\":\n",
    "                self.STORE_NAME(argument)\n",
    "            elif instruction == \"LOAD_NAME\":\n",
    "                self.LOAD_NAME(argument)\n",
    "    \n",
    "    def execute(self, what_to_execute):\n",
    "        instructions = what_to_execute[\"instructions\"]\n",
    "        for each_step in instructions:\n",
    "            instruction, argument = each_step\n",
    "            argument = self.parse_argument(instruction, argument, what_to_execute)\n",
    "            bytecode_method = getattr(self, instruction)\n",
    "            \n",
    "            if argument is None:\n",
    "                bytecode_method()\n",
    "            else:\n",
    "                bytecode_method(argument)"
   ]
  },
  {
   "cell_type": "markdown",
   "metadata": {},
   "source": [
    "7 + 5\n",
    "\n",
    "instructions are:"
   ]
  },
  {
   "cell_type": "code",
   "execution_count": 3,
   "metadata": {},
   "outputs": [],
   "source": [
    "what_to_execute = {\n",
    "    \"instructions\": [(\"LOAD_VALUE\", 0),  # the first number\n",
    "                     (\"LOAD_VALUE\", 1),  # the second number\n",
    "                     (\"ADD_TWO_VALUES\", None),\n",
    "                     (\"PRINT_ANSWER\", None)],\n",
    "    \"numbers\": [7, 5] }"
   ]
  },
  {
   "cell_type": "code",
   "execution_count": 14,
   "metadata": {},
   "outputs": [
    {
     "name": "stdout",
     "output_type": "stream",
     "text": [
      "3\n"
     ]
    }
   ],
   "source": [
    "interpreter = Interpreter()\n",
    "interpreter.run_code(what_to_execute)"
   ]
  },
  {
   "cell_type": "code",
   "execution_count": 15,
   "metadata": {},
   "outputs": [],
   "source": [
    "what_to_execute = {\n",
    "    \"instructions\": [(\"LOAD_VALUE\", 0),\n",
    "                        (\"LOAD_VALUE\", 1),\n",
    "                        (\"ADD_TWO_VALUES\", None),\n",
    "                        (\"LOAD_VALUE\", 2),\n",
    "                        (\"ADD_TWO_VALUES\", None),\n",
    "                        (\"PRINT_ANSWER\", None)],\n",
    "    \"numbers\": [7, 5, 8] }"
   ]
  },
  {
   "cell_type": "code",
   "execution_count": 16,
   "metadata": {},
   "outputs": [
    {
     "name": "stdout",
     "output_type": "stream",
     "text": [
      "20\n"
     ]
    }
   ],
   "source": [
    "interpreter.run_code(what_to_execute)"
   ]
  },
  {
   "cell_type": "code",
   "execution_count": 17,
   "metadata": {},
   "outputs": [],
   "source": [
    "what_to_execute = {\n",
    "    \"instructions\": [(\"LOAD_VALUE\", 0),\n",
    "                        (\"STORE_NAME\", 0),\n",
    "                        (\"LOAD_VALUE\", 1),\n",
    "                        (\"STORE_NAME\", 1),\n",
    "                        (\"LOAD_NAME\", 0),\n",
    "                        (\"LOAD_NAME\", 1),\n",
    "                        (\"ADD_TWO_VALUES\", None),\n",
    "                        (\"PRINT_ANSWER\", None)],\n",
    "    \"numbers\": [1, 2],\n",
    "    \"names\":   [\"a\", \"b\"] }"
   ]
  },
  {
   "cell_type": "code",
   "execution_count": 19,
   "metadata": {},
   "outputs": [
    {
     "name": "stdout",
     "output_type": "stream",
     "text": [
      "3\n"
     ]
    }
   ],
   "source": [
    "interpreter.execute(what_to_execute)"
   ]
  },
  {
   "cell_type": "markdown",
   "metadata": {},
   "source": [
    "Real Python Bytecode"
   ]
  },
  {
   "cell_type": "code",
   "execution_count": 20,
   "metadata": {},
   "outputs": [],
   "source": [
    "def cond():\n",
    "    x = 5\n",
    "    if x > 5:\n",
    "        print(\"True\")\n",
    "    else:\n",
    "        print(\"False\")"
   ]
  },
  {
   "cell_type": "code",
   "execution_count": 21,
   "metadata": {},
   "outputs": [
    {
     "data": {
      "text/plain": [
       "b'd\\x01}\\x00|\\x00d\\x01k\\x04r\\x16t\\x00d\\x02\\x83\\x01\\x01\\x00n\\x08t\\x00d\\x03\\x83\\x01\\x01\\x00d\\x00S\\x00'"
      ]
     },
     "execution_count": 21,
     "metadata": {},
     "output_type": "execute_result"
    }
   ],
   "source": [
    "cond.__code__.co_code"
   ]
  },
  {
   "cell_type": "code",
   "execution_count": 22,
   "metadata": {},
   "outputs": [
    {
     "data": {
      "text/plain": [
       "[100,\n",
       " 1,\n",
       " 125,\n",
       " 0,\n",
       " 124,\n",
       " 0,\n",
       " 100,\n",
       " 1,\n",
       " 107,\n",
       " 4,\n",
       " 114,\n",
       " 22,\n",
       " 116,\n",
       " 0,\n",
       " 100,\n",
       " 2,\n",
       " 131,\n",
       " 1,\n",
       " 1,\n",
       " 0,\n",
       " 110,\n",
       " 8,\n",
       " 116,\n",
       " 0,\n",
       " 100,\n",
       " 3,\n",
       " 131,\n",
       " 1,\n",
       " 1,\n",
       " 0,\n",
       " 100,\n",
       " 0,\n",
       " 83,\n",
       " 0]"
      ]
     },
     "execution_count": 22,
     "metadata": {},
     "output_type": "execute_result"
    }
   ],
   "source": [
    "list(cond.__code__.co_code)"
   ]
  },
  {
   "cell_type": "code",
   "execution_count": 23,
   "metadata": {},
   "outputs": [
    {
     "name": "stdout",
     "output_type": "stream",
     "text": [
      "  2           0 LOAD_CONST               1 (5)\n",
      "              2 STORE_FAST               0 (x)\n",
      "\n",
      "  3           4 LOAD_FAST                0 (x)\n",
      "              6 LOAD_CONST               1 (5)\n",
      "              8 COMPARE_OP               4 (>)\n",
      "             10 POP_JUMP_IF_FALSE       22\n",
      "\n",
      "  4          12 LOAD_GLOBAL              0 (print)\n",
      "             14 LOAD_CONST               2 ('True')\n",
      "             16 CALL_FUNCTION            1\n",
      "             18 POP_TOP\n",
      "             20 JUMP_FORWARD             8 (to 30)\n",
      "\n",
      "  6     >>   22 LOAD_GLOBAL              0 (print)\n",
      "             24 LOAD_CONST               3 ('False')\n",
      "             26 CALL_FUNCTION            1\n",
      "             28 POP_TOP\n",
      "        >>   30 LOAD_CONST               0 (None)\n",
      "             32 RETURN_VALUE\n"
     ]
    }
   ],
   "source": [
    "import dis \n",
    "\n",
    "dis.dis(cond)"
   ]
  },
  {
   "cell_type": "code",
   "execution_count": 29,
   "metadata": {},
   "outputs": [
    {
     "data": {
      "text/plain": [
       "'CALL_FUNCTION'"
      ]
     },
     "execution_count": 29,
     "metadata": {},
     "output_type": "execute_result"
    }
   ],
   "source": [
    "dis.opname[131]"
   ]
  },
  {
   "cell_type": "code",
   "execution_count": 30,
   "metadata": {},
   "outputs": [],
   "source": [
    "def loop():\n",
    "    x = 1\n",
    "    while x < 5:\n",
    "        x = x + 1"
   ]
  },
  {
   "cell_type": "code",
   "execution_count": 31,
   "metadata": {},
   "outputs": [
    {
     "name": "stdout",
     "output_type": "stream",
     "text": [
      "  2           0 LOAD_CONST               1 (1)\n",
      "              2 STORE_FAST               0 (x)\n",
      "\n",
      "  3           4 SETUP_LOOP              20 (to 26)\n",
      "        >>    6 LOAD_FAST                0 (x)\n",
      "              8 LOAD_CONST               2 (5)\n",
      "             10 COMPARE_OP               0 (<)\n",
      "             12 POP_JUMP_IF_FALSE       24\n",
      "\n",
      "  4          14 LOAD_FAST                0 (x)\n",
      "             16 LOAD_CONST               1 (1)\n",
      "             18 BINARY_ADD\n",
      "             20 STORE_FAST               0 (x)\n",
      "             22 JUMP_ABSOLUTE            6\n",
      "        >>   24 POP_BLOCK\n",
      "        >>   26 LOAD_CONST               0 (None)\n",
      "             28 RETURN_VALUE\n"
     ]
    }
   ],
   "source": [
    "dis.dis(loop)"
   ]
  },
  {
   "cell_type": "code",
   "execution_count": 32,
   "metadata": {},
   "outputs": [],
   "source": [
    "def func5():\n",
    "    return 3 + 4\n",
    "\n",
    "def func6():\n",
    "    result = 3 + 4\n",
    "    return result\n"
   ]
  },
  {
   "cell_type": "code",
   "execution_count": 33,
   "metadata": {},
   "outputs": [
    {
     "name": "stdout",
     "output_type": "stream",
     "text": [
      "  2           0 LOAD_CONST               1 (7)\n",
      "              2 RETURN_VALUE\n"
     ]
    }
   ],
   "source": [
    "dis.dis(func5)"
   ]
  },
  {
   "cell_type": "code",
   "execution_count": 34,
   "metadata": {},
   "outputs": [
    {
     "name": "stdout",
     "output_type": "stream",
     "text": [
      "  5           0 LOAD_CONST               1 (7)\n",
      "              2 STORE_FAST               0 (result)\n",
      "\n",
      "  6           4 LOAD_FAST                0 (result)\n",
      "              6 RETURN_VALUE\n"
     ]
    }
   ],
   "source": [
    "dis.dis(func6)"
   ]
  },
  {
   "cell_type": "code",
   "execution_count": null,
   "metadata": {},
   "outputs": [],
   "source": []
  }
 ],
 "metadata": {
  "kernelspec": {
   "display_name": "Python 3",
   "language": "python",
   "name": "python3"
  },
  "language_info": {
   "codemirror_mode": {
    "name": "ipython",
    "version": 3
   },
   "file_extension": ".py",
   "mimetype": "text/x-python",
   "name": "python",
   "nbconvert_exporter": "python",
   "pygments_lexer": "ipython3",
   "version": "3.7.6"
  }
 },
 "nbformat": 4,
 "nbformat_minor": 2
}
